LICENSE
README.rst
setup.py
API_Test_Project/__init__.py
API_Test_Project/conftest.py
API_Test_Project.egg-info/PKG-INFO
API_Test_Project.egg-info/SOURCES.txt
API_Test_Project.egg-info/dependency_links.txt
API_Test_Project.egg-info/top_level.txt
API_Test_Project/common/__init__.py
API_Test_Project/common/http_requests.py
API_Test_Project/common/parse_excel.py
API_Test_Project/common/ws_websocket.py
API_Test_Project/config/__init__.py
API_Test_Project/config/url_config.py
API_Test_Project/fixture/__init__.py
API_Test_Project/fixture/user_api_fixture.py
API_Test_Project/lib/__init__.py
API_Test_Project/main/__init__.py
API_Test_Project/main/run_testcase_by_name.py
API_Test_Project/main/run_testcase_by_tag.py
API_Test_Project/main/run_testcase_collect_only.py
API_Test_Project/report/__init__.py
API_Test_Project/test_case/__init__.py
API_Test_Project/test_case/test_user_api_01.py
API_Test_Project/test_case/test_user_api_02.py
API_Test_Project/test_case/test_user_api_03.py
API_Test_Project/test_case/test_user_api_04.py
API_Test_Project/test_case/test_user_api_05.py
API_Test_Project/test_case/test_user_api_06.py
API_Test_Project/test_data/__init__.py